atomea/__init__.py
atomea/digesters/__init__.py
atomea/digesters/digester.py
atomea/digesters/mdanalysis.py
atomea/digesters/uuids.py
atomea/io/__init__.py
atomea/io/backends/__init__.py
atomea/io/backends/_zarr.py
atomea/io/manager.py
atomea/schemas/__init__.py
atomea/schemas/atomistic/__init__.py
atomea/schemas/atomistic/ensemble.py
atomea/schemas/atomistic/qc.py
atomea/schemas/atomistic/system.py
atomea/schemas/atomistic/topology.py
atomea/schemas/data.py
atomea/schemas/id.py
atomea/schemas/io.py
atomea/schemas/render.py
atomea/schemas/workflow/__init__.py
atomea/schemas/workflow/amber/__init__.py
atomea/schemas/workflow/amber/cli.py
atomea/schemas/workflow/amber/inputs.py
atomea/schemas/workflow/amber/schema.py
atomea/schemas/workflow/amber/v18.py
atomea/schemas/workflow/amber/v20.py
atomea/schemas/workflow/amber/v22.py
atomea/schemas/workflow/ff.py
atomea/schemas/workflow/slurm.py
atomea/schemas/workflow/westpa/__init__.py
atomea/schemas/workflow/westpa/cfg/__init__.py
atomea/schemas/workflow/westpa/cfg/data.py
atomea/schemas/workflow/westpa/cfg/executable.py
atomea/schemas/workflow/westpa/cfg/main.py
atomea/schemas/workflow/westpa/cfg/propagation.py
atomea/schemas/workflow/westpa/cfg/system.py
atomea/schemas/workflow/westpa/cli.py
atomea/schemas/workflow/westpa/environment.py
atomea/schemas/workflow/westpa/main.py
atomea/utils.py
atomea-0.0.0.post171.dist-info/LICENSE.md
atomea-0.0.0.post171.dist-info/METADATA
atomea-0.0.0.post171.dist-info/WHEEL
atomea-0.0.0.post171.dist-info/RECORD
