Metadata-Version: 2.1
Name: atomea
Version: 0.0.0.post171
Summary: Extensible schema for atomistic data and calculations.
License: Apache-2.0
Author: OASCI
Author-email: us@oasci.org
Requires-Python: >=3.10,<4.0
Classifier: License :: OSI Approved :: Apache Software License
Classifier: Programming Language :: Python :: 3
Classifier: Programming Language :: Python :: 3.10
Classifier: Programming Language :: Python :: 3.11
Classifier: Programming Language :: Python :: 3.12
Requires-Dist: loguru (>=0.7.2,<0.8.0)
Requires-Dist: numpy (>=1.26.2,<2.0.0)
Requires-Dist: pydantic (>=2.7.1,<3.0.0)
Requires-Dist: pyyaml (>=6.0.1,<7.0.0)
